katz/__init__.py
katz/imaqt.py
katz-0.1.0.dist-info/WHEEL
katz-0.1.0.dist-info/METADATA
katz-0.1.0.dist-info/RECORD
